{
  "slug": "brother-iprintscan",
  "title": "Brother iPrint&Scan",
  "vendor": "Brother Industries Ltd.",
  "sourceUrl": "https://silentinstallhq.com/brother-iprintscan-silent-install-how-to-guide/",
  "lastScraped": "2026-03-17T02:00:45.866Z",
  "variants": [
    {
      "architecture": "x86/x64",
      "installerType": "EXE",
      "silentInstall": "iPrintScan-Setup-w_x_y_z.exe /install /quiet /norestart",
      "silentUninstall": "iPrintScan-Setup-w_x_y_z.exe /uninstall /quiet /norestart",
      "repair": "iPrintScan-Setup-w_x_y_z.exe /repair /quiet /norestart",
      "downloadUrl": "https://support.brother.com/",
      "psScriptUrl": "https://silentinstallhq.com/brother-iprintscan-install-and-uninstall-powershell/",
      "detectionScriptUrl": "https://silentinstallhq.com/create-a-custom-detection-script-for-brother-iprintscan-powershell/",
      "logInstall": null,
      "logUninstall": null
    }
  ],
  "psadtScript": null
}
