{
  "slug": "calibre",
  "title": "Calibre",
  "vendor": "Kovid Goyal",
  "sourceUrl": "https://silentinstallhq.com/calibre-silent-install-how-to-guide/",
  "lastScraped": "2026-03-17T02:00:56.393Z",
  "variants": [
    {
      "architecture": "x86",
      "installerType": "MSI",
      "silentInstall": "MsiExec.exe /i calibre-x.y.z.msi /qn",
      "silentUninstall": "MsiExec.exe /x calibre-x.y.z.msi /qn",
      "repair": "MsiExec.exe /fa calibre-x.y.z.msi /qn",
      "downloadUrl": "https://calibre-ebook.com/download",
      "psScriptUrl": "https://silentinstallhq.com/calibre-install-and-uninstall-powershell/",
      "detectionScriptUrl": "https://silentinstallhq.com/create-a-custom-detection-script-for-calibre-powershell/",
      "logInstall": null,
      "logUninstall": null
    },
    {
      "architecture": "x64",
      "installerType": "MSI",
      "silentInstall": "MsiExec.exe /i calibre-64bit-x.y.z.msi /qn",
      "silentUninstall": "MsiExec.exe /x calibre-64bit-x.y.z.msi /qn",
      "repair": "MsiExec.exe /fa calibre-64bit-x.y.z.msi /qn",
      "downloadUrl": "https://calibre-ebook.com/download",
      "psScriptUrl": "https://silentinstallhq.com/calibre-install-and-uninstall-powershell/",
      "detectionScriptUrl": "https://silentinstallhq.com/create-a-custom-detection-script-for-calibre-powershell/",
      "logInstall": null,
      "logUninstall": null
    }
  ],
  "psadtScript": null
}
