{
  "slug": "cisco-webex-meetings-desktop-app",
  "title": "Cisco Webex Meetings Desktop App",
  "vendor": "Cisco Webex LLC",
  "sourceUrl": "https://silentinstallhq.com/cisco-webex-meetings-desktop-app-silent-install-how-to-guide/",
  "lastScraped": "2026-03-17T02:01:22.071Z",
  "variants": [
    {
      "architecture": "x86/x64",
      "installerType": "MSI",
      "silentInstall": "MsiExec.exe /i webexapp.msi AUTOOC=0 /qn",
      "silentUninstall": "MsiExec.exe /x webexapp.msi /qn",
      "repair": "MsiExec.exe /fa webexapp.msi AUTOOC=0 /qn",
      "downloadUrl": "https://akamaicdn.webex.com/client/webexapp.msi",
      "psScriptUrl": "https://silentinstallhq.com/cisco-webex-meetings-install-and-uninstall-powershell/",
      "detectionScriptUrl": "https://silentinstallhq.com/create-a-custom-detection-script-for-cisco-webex-meetings-powershell/",
      "logInstall": null,
      "logUninstall": null
    }
  ],
  "psadtScript": null
}
