{
  "slug": "class",
  "title": "Class",
  "vendor": "Class Technologies, Inc.",
  "sourceUrl": "https://silentinstallhq.com/class-silent-install-how-to-guide",
  "lastScraped": "2026-03-16T21:25:35.951Z",
  "variants": [
    {
      "architecture": "x64",
      "installerType": "MSI",
      "silentInstall": "MsiExec.exe /i Class.msi /qn",
      "silentUninstall": "MsiExec.exe /x Class.msi /qn",
      "repair": "MsiExec.exe /fa Class.msi /qn",
      "downloadUrl": "https://download.class.com/windows/Class.msi",
      "psScriptUrl": null,
      "detectionScriptUrl": null,
      "logInstall": null,
      "logUninstall": null
    }
  ]
}
