{
  "slug": "deezer-desktop",
  "title": "Deezer Desktop",
  "vendor": "Deezer",
  "sourceUrl": "https://silentinstallhq.com/deezer-desktop-silent-install-how-to-guide/",
  "lastScraped": "2026-03-17T02:02:48.127Z",
  "variants": [
    {
      "architecture": "x86/x64",
      "installerType": "EXE",
      "silentInstall": "DeezerDesktopSetup_x.y.z.exe /S",
      "silentUninstall": "\"%LocalAppData%\\Programs\\deezer-desktop\\Uninstall Deezer.exe\" /S",
      "repair": null,
      "downloadUrl": "https://www.deezer.com/desktop/download?platform=win32&architecture=x86",
      "psScriptUrl": null,
      "detectionScriptUrl": null,
      "logInstall": null,
      "logUninstall": null
    }
  ],
  "psadtScript": null
}
