{
  "slug": "ppsspp",
  "title": "PPSSPP",
  "vendor": "PPSSPP Team",
  "sourceUrl": "https://silentinstallhq.com/ppsspp-silent-install-how-to-guide/",
  "lastScraped": "2026-03-17T02:29:43.853Z",
  "variants": [
    {
      "architecture": "x86/x64",
      "installerType": "EXE",
      "silentInstall": "PPSSPPSetup.exe /VERYSILENT /NORESTART",
      "silentUninstall": "\"%ProgramFiles%\\PPSSPP\\unins000.exe\" /VERYSILENT /NORESTART",
      "repair": null,
      "downloadUrl": "https://www.ppsspp.org/downloads_all.html#windows",
      "psScriptUrl": null,
      "detectionScriptUrl": null,
      "logInstall": null,
      "logUninstall": null
    }
  ],
  "psadtScript": null
}
