{
  "slug": "x2go-client",
  "title": "X2Go Client",
  "vendor": "X2Go Project",
  "sourceUrl": "https://silentinstallhq.com/x2go-client-silent-install-how-to-guide/",
  "lastScraped": "2026-03-17T02:32:30.422Z",
  "variants": [
    {
      "architecture": "x86",
      "installerType": "EXE",
      "silentInstall": "x2goclient-w.x.y.z-setup.exe /S",
      "silentUninstall": "",
      "repair": null,
      "downloadUrl": "https://code.x2go.org/releases/binary-win32/x2goclient/releases",
      "psScriptUrl": "https://silentinstallhq.com/x2go-client-install-and-uninstall-powershell/",
      "detectionScriptUrl": null,
      "logInstall": null,
      "logUninstall": null
    }
  ],
  "psadtScript": null
}
